<?xml version="1.0" encoding="utf-8"?><HelpTOCNode Title="CursorTooltipSettingsState Properties" Url="html/BD5D5EE1.htm"><HelpTOCNode Title="AutoSuppress Property " Url="html/1684B428.htm" /><HelpTOCNode Title="BackgroundColor Property " Url="html/647E57BF.htm" /><HelpTOCNode Title="CommandPromptPane Property " Url="html/B8DFBBD.htm" /><HelpTOCNode Title="DistancePane Property " Url="html/78E283DD.htm" /><HelpTOCNode Title="Offset Property " Url="html/6F16A609.htm" /><HelpTOCNode Title="OsnapPane Property " Url="html/22BB63A1.htm" /><HelpTOCNode Title="PointPane Property " Url="html/A833000.htm" /><HelpTOCNode Title="RelativePointPane Property " Url="html/78200D0C.htm" /><HelpTOCNode Title="TextColor Property " Url="html/936EAE1A.htm" /><HelpTOCNode Title="TooltipsEnabled Property " Url="html/22777D63.htm" /></HelpTOCNode>