<?xml version="1.0" encoding="utf-8"?><HelpTOCNode Title="RhinoDoc Properties" Url="html/Properties_T_Rhino_RhinoDoc.htm"><HelpTOCNode Title="ActiveDoc Property " Url="html/P_Rhino_RhinoDoc_ActiveDoc.htm" /><HelpTOCNode Title="Bitmaps Property " Url="html/P_Rhino_RhinoDoc_Bitmaps.htm" /><HelpTOCNode Title="DateCreated Property " Url="html/P_Rhino_RhinoDoc_DateCreated.htm" /><HelpTOCNode Title="DateLastEdited Property " Url="html/P_Rhino_RhinoDoc_DateLastEdited.htm" /><HelpTOCNode Title="DimStyles Property " Url="html/P_Rhino_RhinoDoc_DimStyles.htm" /><HelpTOCNode Title="DistanceDisplayPrecision Property " Url="html/P_Rhino_RhinoDoc_DistanceDisplayPrecision.htm" /><HelpTOCNode Title="DocumentId Property " Url="html/P_Rhino_RhinoDoc_DocumentId.htm" /><HelpTOCNode Title="EarthAnchorPoint Property " Url="html/P_Rhino_RhinoDoc_EarthAnchorPoint.htm" /><HelpTOCNode Title="Fonts Property " Url="html/P_Rhino_RhinoDoc_Fonts.htm" /><HelpTOCNode Title="Groups Property " Url="html/P_Rhino_RhinoDoc_Groups.htm" /><HelpTOCNode Title="HatchPatterns Property " Url="html/P_Rhino_RhinoDoc_HatchPatterns.htm" /><HelpTOCNode Title="InstanceDefinitions Property " Url="html/P_Rhino_RhinoDoc_InstanceDefinitions.htm" /><HelpTOCNode Title="IsLocked Property " Url="html/P_Rhino_RhinoDoc_IsLocked.htm" /><HelpTOCNode Title="IsReadOnly Property " Url="html/P_Rhino_RhinoDoc_IsReadOnly.htm" /><HelpTOCNode Title="IsSendingMail Property " Url="html/P_Rhino_RhinoDoc_IsSendingMail.htm" /><HelpTOCNode Title="Layers Property " Url="html/P_Rhino_RhinoDoc_Layers.htm" /><HelpTOCNode Title="Lights Property " Url="html/P_Rhino_RhinoDoc_Lights.htm" /><HelpTOCNode Title="Linetypes Property " Url="html/P_Rhino_RhinoDoc_Linetypes.htm" /><HelpTOCNode Title="Materials Property " Url="html/P_Rhino_RhinoDoc_Materials.htm" /><HelpTOCNode Title="MeshingParameterStyle Property " Url="html/P_Rhino_RhinoDoc_MeshingParameterStyle.htm" /><HelpTOCNode Title="ModelAbsoluteTolerance Property " Url="html/P_Rhino_RhinoDoc_ModelAbsoluteTolerance.htm" /><HelpTOCNode Title="ModelAngleToleranceDegrees Property " Url="html/P_Rhino_RhinoDoc_ModelAngleToleranceDegrees.htm" /><HelpTOCNode Title="ModelAngleToleranceRadians Property " Url="html/P_Rhino_RhinoDoc_ModelAngleToleranceRadians.htm" /><HelpTOCNode Title="ModelDistanceDisplayPrecision Property " Url="html/P_Rhino_RhinoDoc_ModelDistanceDisplayPrecision.htm" /><HelpTOCNode Title="ModelRelativeTolerance Property " Url="html/P_Rhino_RhinoDoc_ModelRelativeTolerance.htm" /><HelpTOCNode Title="ModelUnitSystem Property " Url="html/P_Rhino_RhinoDoc_ModelUnitSystem.htm" /><HelpTOCNode Title="Modified Property " Url="html/P_Rhino_RhinoDoc_Modified.htm" /><HelpTOCNode Title="Name Property " Url="html/P_Rhino_RhinoDoc_Name.htm" /><HelpTOCNode Title="NamedConstructionPlanes Property " Url="html/P_Rhino_RhinoDoc_NamedConstructionPlanes.htm" /><HelpTOCNode Title="NamedViews Property " Url="html/P_Rhino_RhinoDoc_NamedViews.htm" /><HelpTOCNode Title="Notes Property " Url="html/P_Rhino_RhinoDoc_Notes.htm" /><HelpTOCNode Title="Objects Property " Url="html/P_Rhino_RhinoDoc_Objects.htm" /><HelpTOCNode Title="PageAbsoluteTolerance Property " Url="html/P_Rhino_RhinoDoc_PageAbsoluteTolerance.htm" /><HelpTOCNode Title="PageAngleToleranceDegrees Property " Url="html/P_Rhino_RhinoDoc_PageAngleToleranceDegrees.htm" /><HelpTOCNode Title="PageAngleToleranceRadians Property " Url="html/P_Rhino_RhinoDoc_PageAngleToleranceRadians.htm" /><HelpTOCNode Title="PageDistanceDisplayPrecision Property " Url="html/P_Rhino_RhinoDoc_PageDistanceDisplayPrecision.htm" /><HelpTOCNode Title="PageRelativeTolerance Property " Url="html/P_Rhino_RhinoDoc_PageRelativeTolerance.htm" /><HelpTOCNode Title="PageUnitSystem Property " Url="html/P_Rhino_RhinoDoc_PageUnitSystem.htm" /><HelpTOCNode Title="Path Property " Url="html/P_Rhino_RhinoDoc_Path.htm" /><HelpTOCNode Title="RenderSettings Property " Url="html/P_Rhino_RhinoDoc_RenderSettings.htm" /><HelpTOCNode Title="RuntimeSerialNumber Property " Url="html/P_Rhino_RhinoDoc_RuntimeSerialNumber.htm" /><HelpTOCNode Title="Strings Property " Url="html/P_Rhino_RhinoDoc_Strings.htm" /><HelpTOCNode Title="TemplateFileUsed Property " Url="html/P_Rhino_RhinoDoc_TemplateFileUsed.htm" /><HelpTOCNode Title="UndoRecordingEnabled Property " Url="html/P_Rhino_RhinoDoc_UndoRecordingEnabled.htm" /><HelpTOCNode Title="UndoRecordingIsActive Property " Url="html/P_Rhino_RhinoDoc_UndoRecordingIsActive.htm" /><HelpTOCNode Title="Views Property " Url="html/P_Rhino_RhinoDoc_Views.htm" /></HelpTOCNode>